nkpack/__init__.py
nkpack/funcspace.py
nkpack-1.5.8.dist-info/LICENSE
nkpack-1.5.8.dist-info/METADATA
nkpack-1.5.8.dist-info/WHEEL
nkpack-1.5.8.dist-info/top_level.txt
nkpack-1.5.8.dist-info/RECORD
