Metadata-Version: 2.1
Name: nkpack
Version: 1.5.8
Summary: Utilities library for agent-based modeling using NK-framework
Home-page: https://github.com/ravshansk/nkpack
Author: Ravshan S.K.
Author-email: rsk@ravshansk.com
License: UNKNOWN
Platform: UNKNOWN
Classifier: Programming Language :: Python :: 3
Classifier: License :: OSI Approved :: MIT License
Classifier: Operating System :: OS Independent
Requires-Python: >=3.6
License-File: LICENSE
